octopi/__init__.py
octopi/main.py
octopi/workflows.py
octopi/datasets/__init__.py
octopi/datasets/augment.py
octopi/datasets/cached_datset.py
octopi/datasets/dataset.py
octopi/datasets/generators.py
octopi/datasets/io.py
octopi/datasets/mixup.py
octopi/datasets/multi_config_generator.py
octopi/entry_points/__init__.py
octopi/entry_points/common.py
octopi/entry_points/create_slurm_submission.py
octopi/entry_points/run_create_targets.py
octopi/entry_points/run_evaluate.py
octopi/entry_points/run_extract_mb_picks.py
octopi/entry_points/run_extract_midpoint.py
octopi/entry_points/run_localize.py
octopi/entry_points/run_optuna.py
octopi/entry_points/run_segment_predict.py
octopi/entry_points/run_train.py
octopi/extract/__init__.py
octopi/extract/localize.py
octopi/extract/membranebound_extract.py
octopi/extract/midpoint_extract.py
octopi/models/AttentionUnet.py
octopi/models/MedNeXt.py
octopi/models/ModelTemplate.py
octopi/models/SegResNet.py
octopi/models/Unet.py
octopi/models/UnetPlusPlus.py
octopi/models/__init__.py
octopi/models/common.py
octopi/processing/__init__.py
octopi/processing/create_targets_from_picks.py
octopi/processing/downsample.py
octopi/processing/evaluate.py
octopi/processing/importers.py
octopi/processing/segmentation_from_picks.py
octopi/pytorch/__init__.py
octopi/pytorch/hyper_search.py
octopi/pytorch/model_search_submitter.py
octopi/pytorch/segmentation.py
octopi/pytorch/segmentation_multigpu.py
octopi/pytorch/trainer.py
octopi/pytorch_lightning/__init__.py
octopi/pytorch_lightning/optuna_pl_ddp.py
octopi/pytorch_lightning/train_pl.py
octopi/utils/__init__.py
octopi/utils/config.py
octopi/utils/io.py
octopi/utils/losses.py
octopi/utils/parsers.py
octopi/utils/stopping_criteria.py
octopi/utils/submit_slurm.py
octopi/utils/visualization_tools.py
octopi-1.3.3.dist-info/METADATA
octopi-1.3.3.dist-info/WHEEL
octopi-1.3.3.dist-info/entry_points.txt
octopi-1.3.3.dist-info/licenses/LICENSE
octopi-1.3.3.dist-info/RECORD
