Metadata-Version: 2.4
Name: octopi
Version: 1.3.3
Summary: Model architecture exploration for cryoET particle picking
Project-URL: Homepage, https://github.com/chanzuckerberg/octopi
Project-URL: Documentation, https://chanzuckerberg.github.io/octopi/
Project-URL: Issues, https://github.com/chanzuckerberg/octopi/issues
Author: Jonathan Schwartz, Kevin Zhao, Daniel Ji, Utz Ermel
License: MIT
License-File: LICENSE
Classifier: License :: OSI Approved :: MIT License
Classifier: Programming Language :: Python :: 3
Classifier: Programming Language :: Python :: 3.9
Classifier: Programming Language :: Python :: 3.10
Classifier: Programming Language :: Python :: 3.11
Classifier: Programming Language :: Python :: 3.12
Classifier: Programming Language :: Python :: 3.13
Classifier: Topic :: Scientific/Engineering :: Artificial Intelligence
Classifier: Topic :: Scientific/Engineering :: Image Processing
Classifier: Topic :: Scientific/Engineering :: Image Recognition
Requires-Python: >=3.9
Requires-Dist: copick
Requires-Dist: copick-utils
Requires-Dist: ipywidgets
Requires-Dist: kaleido
Requires-Dist: matplotlib
Requires-Dist: mlflow
Requires-Dist: monai
Requires-Dist: mrcfile
Requires-Dist: multiprocess
Requires-Dist: nibabel
Requires-Dist: optuna
Requires-Dist: optuna-integration[botorch,pytorch-lightning]
Requires-Dist: pandas
Requires-Dist: python-dotenv
Requires-Dist: requests
Requires-Dist: torch-ema
Requires-Dist: tqdm
Provides-Extra: dev
Requires-Dist: black>=24.8.0; extra == 'dev'
Requires-Dist: pre-commit>=3.8.0; extra == 'dev'
Requires-Dist: pytest>=6.2.3; extra == 'dev'
Requires-Dist: ruff>=0.6.4; extra == 'dev'
Provides-Extra: docs
Requires-Dist: mkdocs; extra == 'docs'
Requires-Dist: mkdocs-awesome-pages-plugin; extra == 'docs'
Requires-Dist: mkdocs-git-authors-plugin; extra == 'docs'
Requires-Dist: mkdocs-git-committers-plugin-2; extra == 'docs'
Requires-Dist: mkdocs-git-revision-date-localized-plugin; extra == 'docs'
Requires-Dist: mkdocs-material; extra == 'docs'
Requires-Dist: mkdocs-minify-plugin; extra == 'docs'
Requires-Dist: mkdocs-redirects; extra == 'docs'
